lumos/__init__.py
lumos/evaluation.py
lumos/extraction.py
lumos/models.py
lumos/segmentation.py
lumos_salience-1.0.0.dist-info/METADATA
lumos_salience-1.0.0.dist-info/WHEEL
lumos_salience-1.0.0.dist-info/licenses/LICENSE
lumos_salience-1.0.0.dist-info/RECORD
