Metadata-Version: 2.4
Name: lumos-salience
Version: 1.0.0
Summary: LLM-based Universal Measure Of Salience - Testing LLMs' ability to capture image salience
Project-URL: Repository, http://github.com/NNyarlathotep/Lumos-Salience
Project-URL: Issues, https://github.com/NNyarlathotep/Lumos-Salience/issues
Author-email: Cantay Caliskan <ccaliska@ur.rochester.edu>, Zhizhuang Chen <zchen141@u.rochester.edu>
License: MIT
License-File: LICENSE
Keywords: Computer Vision,Image Segmentation,Large Language Model,Saliency Detection
Classifier: Development Status :: 4 - Beta
Classifier: Intended Audience :: Science/Research
Classifier: License :: OSI Approved :: MIT License
Classifier: Operating System :: OS Independent
Classifier: Programming Language :: Python :: 3.11
Classifier: Topic :: Scientific/Engineering :: Artificial Intelligence
Classifier: Topic :: Scientific/Engineering :: Image Recognition
Requires-Python: >=3.8
Requires-Dist: accelerate>=0.20.0
Requires-Dist: numpy>=1.19.0
Requires-Dist: opencv-python>=4.5.0
Requires-Dist: pandas>=1.3.0
Requires-Dist: pillow>=8.0.0
Requires-Dist: requests>=2.25.0
Requires-Dist: torch>=2.0.0
Requires-Dist: tqdm>=4.60.0
Requires-Dist: transformers>=4.30.0
